PhpKuozhanKaifaRumen/README.md
PhpKuozhanKaifaRumen/__init__.py
PhpKuozhanKaifaRumen/__main__.py
PhpKuozhanKaifaRumen/file.epub
PhpKuozhanKaifaRumen/index.html
PhpKuozhanKaifaRumen/css/__init__.py
PhpKuozhanKaifaRumen/css/annotations.css
PhpKuozhanKaifaRumen/css/main.css
PhpKuozhanKaifaRumen/css/normalize.css
PhpKuozhanKaifaRumen/css/popup.css
PhpKuozhanKaifaRumen/font/__init__.py
PhpKuozhanKaifaRumen/font/fontello.eot
PhpKuozhanKaifaRumen/font/fontello.svg
PhpKuozhanKaifaRumen/font/fontello.ttf
PhpKuozhanKaifaRumen/font/fontello.woff
PhpKuozhanKaifaRumen/img/__init__.py
PhpKuozhanKaifaRumen/img/annotator-glyph-sprite.png
PhpKuozhanKaifaRumen/img/annotator-icon-sprite.png
PhpKuozhanKaifaRumen/img/apple-touch-icon.png
PhpKuozhanKaifaRumen/img/cancelfullscreen.png
PhpKuozhanKaifaRumen/img/close.png
PhpKuozhanKaifaRumen/img/fullscreen.png
PhpKuozhanKaifaRumen/img/loader.gif
PhpKuozhanKaifaRumen/img/menu-icon.png
PhpKuozhanKaifaRumen/img/save.png
PhpKuozhanKaifaRumen/img/saved.png
PhpKuozhanKaifaRumen/img/settings-s.png
PhpKuozhanKaifaRumen/img/settings.png
PhpKuozhanKaifaRumen/img/star.png
PhpKuozhanKaifaRumen/js/__init__.py
PhpKuozhanKaifaRumen/js/epub.js
PhpKuozhanKaifaRumen/js/epub.min.js
PhpKuozhanKaifaRumen/js/epub.min.map
PhpKuozhanKaifaRumen/js/hooks.min.js
PhpKuozhanKaifaRumen/js/hooks.min.map
PhpKuozhanKaifaRumen/js/reader.js
PhpKuozhanKaifaRumen/js/reader.js.map
PhpKuozhanKaifaRumen/js/reader.min.js
PhpKuozhanKaifaRumen/js/reader.min.map
PhpKuozhanKaifaRumen/js/hooks/__init__.py
PhpKuozhanKaifaRumen/js/hooks/extensions/__init__.py
PhpKuozhanKaifaRumen/js/hooks/extensions/highlight.js
PhpKuozhanKaifaRumen/js/libs/__init__.py
PhpKuozhanKaifaRumen/js/libs/jquery.min.js
PhpKuozhanKaifaRumen/js/libs/localforage.min.js
PhpKuozhanKaifaRumen/js/libs/screenfull.js
PhpKuozhanKaifaRumen/js/libs/screenfull.min.js
PhpKuozhanKaifaRumen/js/libs/zip.min.js
PhpKuozhanKaifaRumen/js/plugins/__init__.py
PhpKuozhanKaifaRumen/js/plugins/hypothesis.js
php_kuozhan_kaifa_rumen-2024.3.3.0.dist-info/METADATA
php_kuozhan_kaifa_rumen-2024.3.3.0.dist-info/WHEEL
php_kuozhan_kaifa_rumen-2024.3.3.0.dist-info/entry_points.txt
php_kuozhan_kaifa_rumen-2024.3.3.0.dist-info/top_level.txt
php_kuozhan_kaifa_rumen-2024.3.3.0.dist-info/RECORD
